mcp_mode/README.md
mcp_mode/__init__.py
mcp_mode/mcp_client/mcp_client_example.py
mcp_mode/mcp_server/__init__.py
mcp_mode/mcp_server/app_device_mapping.json
mcp_mode/mcp_server/model_config.yaml
mcp_mode/mcp_server/order_wise_mcp_backend.py
mcp_mode/mcp_server/order_wise_mcp_server.py
mcp_mode/mcp_server/server_config.yaml
mcp_mode/mcp_server/session_manager.py
orderwise_agent/__init__.py
orderwise_agent/__main__.py
orderwise_agent/cli/__init__.py
orderwise_agent/cli/mcp.py
orderwise_agent/cli/mcp_server.py
orderwise_agent/cli/utils.py
orderwise_agent/core/__init__.py
orderwise_agent/core/compare.py
orderwise_agent-1.0.2.data/data/NOTICE
orderwise_agent-1.0.2.data/data/README.md
orderwise_agent-1.0.2.data/data/requirements.txt
orderwise_agent-1.0.2.data/data/examples/__init__.py
orderwise_agent-1.0.2.data/data/examples/app_device_mapping.json
orderwise_agent-1.0.2.data/data/examples/apps_config.json
orderwise_agent-1.0.2.data/data/examples/basic_usage.py
orderwise_agent-1.0.2.data/data/examples/demo_thinking.py
orderwise_agent-1.0.2.data/data/examples/sdk_usage.py
phone_agent/__init__.py
phone_agent/agent.py
phone_agent/actions/__init__.py
phone_agent/actions/handler.py
phone_agent/adb/__init__.py
phone_agent/adb/connection.py
phone_agent/adb/device.py
phone_agent/adb/input.py
phone_agent/adb/screenshot.py
phone_agent/config/__init__.py
phone_agent/config/apps.py
phone_agent/config/i18n.py
phone_agent/config/listener_devices.py
phone_agent/config/prompts.py
phone_agent/config/prompts_en.py
phone_agent/config/prompts_zh.py
phone_agent/model/__init__.py
phone_agent/model/client.py
phone_agent/utils/__init__.py
phone_agent/utils/device_manager.py
phone_agent/utils/mongodb_listener.py
phone_agent/utils/mongodb_writer.py
phone_agent/utils/orderwise_logger.py
phone_agent/utils/parallel_executor.py
phone_agent/utils/price_extractor.py
phone_agent/utils/screenshot_cache.py
orderwise_agent-1.0.2.dist-info/METADATA
orderwise_agent-1.0.2.dist-info/WHEEL
orderwise_agent-1.0.2.dist-info/entry_points.txt
orderwise_agent-1.0.2.dist-info/top_level.txt
orderwise_agent-1.0.2.dist-info/RECORD
