Metadata-Version: 2.4
Name: orderwise-agent
Version: 1.0.2
Summary: 基于 AutoGLM 的智能外卖比价 Agent
Home-page: https://github.com/ucloud/orderwise-agent
Author: UCloud
Author-email: UCloud <orderwise.agent@gmail.com>
License: Apache-2.0
Project-URL: Homepage, https://github.com/ucloud/orderwise-agent
Project-URL: Repository, https://github.com/ucloud/orderwise-agent
Keywords: ai,agent,mobile,automation,price-comparison
Classifier: Development Status :: 4 - Beta
Classifier: Intended Audience :: Developers
Classifier: License :: OSI Approved :: Apache Software License
Classifier: Operating System :: OS Independent
Classifier: Programming Language :: Python :: 3
Classifier: Programming Language :: Python :: 3.10
Classifier: Programming Language :: Python :: 3.11
Classifier: Programming Language :: Python :: 3.12
Classifier: Topic :: Software Development :: Libraries :: Python Modules
Classifier: Topic :: Scientific/Engineering :: Artificial Intelligence
Requires-Python: >=3.10
Requires-Dist: PyYAML>=6.0
Requires-Dist: Pillow>=12.0.0
Requires-Dist: pydantic>=2.12.5
Requires-Dist: openai>=2.9.0
Requires-Dist: pymongo>=4.15.5
Requires-Dist: starlette>=0.50.0
Requires-Dist: mcp>=1.0.0
Requires-Dist: fastmcp>=0.1.0
Requires-Dist: uvicorn>=0.20.0
Provides-Extra: dev
Requires-Dist: pytest>=7.0.0; extra == "dev"
Requires-Dist: black>=23.0.0; extra == "dev"
Requires-Dist: ruff>=0.1.0; extra == "dev"
Dynamic: author
Dynamic: home-page
Dynamic: requires-python
